jupyter_dashboard/__init__.py
jupyter_dashboard/__main__.py
jupyter_dashboard/_version.py
jupyter_dashboard/application.py
jupyter_dashboard/serverapplication.py
jupyter_dashboard/handlers/__init__.py
jupyter_dashboard/handlers/base.py
jupyter_dashboard/handlers/config/__init__.py
jupyter_dashboard/handlers/config/handler.py
jupyter_dashboard/handlers/index/__init__.py
jupyter_dashboard/handlers/index/handler.py
jupyter_dashboard/static/README.md
jupyter_dashboard/static/main.jupyter-dashboard.js
jupyter_dashboard/templates/index.html
jupyter_dashboard/tests/__init__.py
jupyter_dashboard/tests/test_handlers.py
jupyter_dashboard-0.0.4.data/data/etc/jupyter/jupyter_notebook_config.d/jupyter_dashboard.json
jupyter_dashboard-0.0.4.data/data/etc/jupyter/jupyter_server_config.d/jupyter_dashboard.json
jupyter_dashboard-0.0.4.data/data/share/jupyter/labextensions/@datalayer/jupyter-dashboard/build_log.json
jupyter_dashboard-0.0.4.data/data/share/jupyter/labextensions/@datalayer/jupyter-dashboard/package.json
jupyter_dashboard-0.0.4.data/data/share/jupyter/labextensions/@datalayer/jupyter-dashboard/schemas/@datalayer/jupyter-dashboard/package.json.orig
jupyter_dashboard-0.0.4.data/data/share/jupyter/labextensions/@datalayer/jupyter-dashboard/schemas/@datalayer/jupyter-dashboard/plugin.json
jupyter_dashboard-0.0.4.data/data/share/jupyter/labextensions/@datalayer/jupyter-dashboard/static/lib_index_js-webpack_sharing_consume_default_react-dom-webpack_sharing_consume_default_react.66001d1350632a94295d.js
jupyter_dashboard-0.0.4.data/data/share/jupyter/labextensions/@datalayer/jupyter-dashboard/static/lib_index_js-webpack_sharing_consume_default_react-dom-webpack_sharing_consume_default_react.66001d1350632a94295d.js.map
jupyter_dashboard-0.0.4.data/data/share/jupyter/labextensions/@datalayer/jupyter-dashboard/static/remoteEntry.e545258c81636aa4d09a.js
jupyter_dashboard-0.0.4.dist-info/METADATA
jupyter_dashboard-0.0.4.dist-info/WHEEL
jupyter_dashboard-0.0.4.dist-info/entry_points.txt
jupyter_dashboard-0.0.4.dist-info/licenses/LICENSE
jupyter_dashboard-0.0.4.dist-info/RECORD
